caft/__init__.py
caft/affine.py
caft/exceptions.py
caft/odr.py
caft/regressors.py
caft/utils.py
tests/__init__.py
tests/tests_caft/__init__.py
tests/tests_caft/test_affine.py
tests/tests_caft/test_odr.py
tests/tests_caft/test_regressors.py
tests/tests_caft/test_utils.py
caft-0.1.9.dist-info/LICENSE
caft-0.1.9.dist-info/METADATA
caft-0.1.9.dist-info/WHEEL
caft-0.1.9.dist-info/top_level.txt
caft-0.1.9.dist-info/RECORD
