Metadata-Version: 2.1
Name: caft
Version: 0.1.9
Summary: Continuous Affine Feature Transformations for feature mapping.
Home-page: https://github.com/joshdunnlime/caft
Author: Joshua Dunn
Author-email: joshua.t.dunn@hotmail.co.uk
Project-URL: Documentation, https://github.com/joshdunnlime/caft
Project-URL: Bug Reports, https://github.com/joshdunnlime/caft/issues
Project-URL: Source Code, https://github.com/joshdunnlime/caft
Keywords: feature-engineering feature-mapping,anomaly-detection
Classifier: Development Status :: 5 - Production/Stable
Classifier: Intended Audience :: Developers
Classifier: Topic :: Software Development :: Build Tools
Classifier: Programming Language :: Python :: 3.8
Classifier: Programming Language :: Python :: 3.9
Classifier: Programming Language :: Python :: 3.10
Classifier: Programming Language :: Python :: 3 :: Only
Classifier: License :: OSI Approved :: MIT License
Classifier: Operating System :: OS Independent
Requires-Python: >=3.8
License-File: LICENSE
Requires-Dist: sympy (>=1.11.0)
Requires-Dist: pandas (>=1.3.0)
Requires-Dist: scikit-learn (>=1.0.0)
Provides-Extra: dev
Requires-Dist: check-manifest ; extra == 'dev'
